{"chunk_definitions":[{"row":25,"row_count":1,"visible":true,"expansion_state":0,"options":{"engine":"r","label":"unnamed-chunk-1"},"document_id":"79BC640A","chunk_id":"cfgziy1tu12ff","chunk_label":"unnamed-chunk-1"},{"row":35,"row_count":1,"visible":true,"expansion_state":0,"options":{},"document_id":"79BC640A","chunk_id":"c5pqzyfdzvhju","chunk_label":"unnamed-chunk-2"},{"row":44,"row_count":1,"visible":true,"expansion_state":0,"options":{},"document_id":"79BC640A","chunk_id":"cbkvlhzyn0f8b","chunk_label":"unnamed-chunk-3"},{"row":53,"row_count":1,"visible":true,"expansion_state":0,"options":{},"document_id":"79BC640A","chunk_id":"csxligamzcusw","chunk_label":"unnamed-chunk-4"},{"row":66,"row_count":1,"visible":true,"expansion_state":0,"options":{},"document_id":"79BC640A","chunk_id":"cn7nfffbmdpdd","chunk_label":"unnamed-chunk-5"},{"row":81,"row_count":1,"visible":true,"expansion_state":0,"options":{},"document_id":"79BC640A","chunk_id":"cjmhoium9r5wp","chunk_label":"unnamed-chunk-6"},{"row":89,"row_count":1,"visible":true,"expansion_state":0,"options":{},"document_id":"79BC640A","chunk_id":"cv7u7igwzti6y","chunk_label":"unnamed-chunk-7"},{"row":103,"row_count":1,"visible":true,"expansion_state":0,"options":{},"document_id":"79BC640A","chunk_id":"chghwzkggeaqi","chunk_label":"unnamed-chunk-8"},{"row":127,"row_count":1,"visible":true,"expansion_state":0,"options":{},"document_id":"79BC640A","chunk_id":"cndyz0uz3do0c","chunk_label":"unnamed-chunk-9"},{"row":133,"row_count":1,"visible":true,"expansion_state":0,"options":{},"document_id":"79BC640A","chunk_id":"cvzq8h1jig323","chunk_label":"unnamed-chunk-10"},{"row":142,"row_count":1,"visible":true,"expansion_state":0,"options":{},"document_id":"79BC640A","chunk_id":"cad4pbzrd8sw3","chunk_label":"unnamed-chunk-11"},{"row":155,"row_count":1,"visible":true,"expansion_state":0,"options":{},"document_id":"79BC640A","chunk_id":"cn35qaevtfkxw","chunk_label":"unnamed-chunk-12"},{"row":170,"row_count":1,"visible":true,"expansion_state":0,"options":{},"document_id":"79BC640A","chunk_id":"cts25l30glsq7","chunk_label":"unnamed-chunk-13"},{"row":186,"row_count":1,"visible":true,"expansion_state":0,"options":{},"document_id":"79BC640A","chunk_id":"cv6ceta1m0qz9","chunk_label":"unnamed-chunk-14"},{"row":198,"row_count":1,"visible":true,"expansion_state":0,"options":{},"document_id":"79BC640A","chunk_id":"cz6u4hdfwce5q","chunk_label":"unnamed-chunk-15"},{"row":210,"row_count":1,"visible":true,"expansion_state":0,"options":{},"document_id":"79BC640A","chunk_id":"corr0k10u2u7g","chunk_label":"unnamed-chunk-16"},{"row":226,"row_count":1,"visible":true,"expansion_state":0,"options":{},"document_id":"79BC640A","chunk_id":"cvxo7ilinz01f","chunk_label":"unnamed-chunk-17"},{"row":242,"row_count":1,"visible":true,"expansion_state":0,"options":{},"document_id":"79BC640A","chunk_id":"ckeaxxpr0t6ez","chunk_label":"unnamed-chunk-18"},{"row":251,"row_count":1,"visible":true,"expansion_state":0,"options":{},"document_id":"79BC640A","chunk_id":"c4cx4nadzdlt2","chunk_label":"unnamed-chunk-19"},{"row":258,"row_count":1,"visible":true,"expansion_state":0,"options":{},"document_id":"79BC640A","chunk_id":"cnqixywwa8l83","chunk_label":"unnamed-chunk-20"},{"row":265,"row_count":1,"visible":true,"expansion_state":0,"options":{},"document_id":"79BC640A","chunk_id":"c8al0kjaddskm","chunk_label":"unnamed-chunk-21"},{"row":276,"row_count":1,"visible":true,"expansion_state":0,"options":{},"document_id":"79BC640A","chunk_id":"cmm7ruf4aoy16","chunk_label":"unnamed-chunk-22"},{"row":288,"row_count":1,"visible":true,"expansion_state":0,"options":{},"document_id":"79BC640A","chunk_id":"ck4eqho0kqox7","chunk_label":"unnamed-chunk-23"},{"row":298,"row_count":1,"visible":true,"expansion_state":0,"options":{},"document_id":"79BC640A","chunk_id":"cfw18oskg07fo","chunk_label":"unnamed-chunk-24"},{"row":312,"row_count":1,"visible":true,"expansion_state":0,"options":{},"document_id":"79BC640A","chunk_id":"cdzhoaojlzbyb","chunk_label":"unnamed-chunk-25"},{"row":323,"row_count":1,"visible":true,"expansion_state":0,"options":{},"document_id":"79BC640A","chunk_id":"crjvfm4gwtnf9","chunk_label":"unnamed-chunk-26"}],"doc_write_time":1618160097,"chunk_rendered_width":700}