{"chunk_definitions":[{"row":14,"row_count":1,"visible":true,"expansion_state":0,"options":{"engine":"r","label":"unnamed-chunk-7"},"document_id":"B93345BE","chunk_id":"cp7zt4vpjbuy9","chunk_label":"unnamed-chunk-1"},{"row":20,"row_count":1,"visible":true,"expansion_state":0,"options":{},"document_id":"B93345BE","chunk_id":"cq3qx0hzas86f","chunk_label":"unnamed-chunk-2"},{"row":27,"row_count":1,"visible":true,"expansion_state":0,"options":{},"document_id":"B93345BE","chunk_id":"ckkaj1stqoku7","chunk_label":"unnamed-chunk-3"},{"row":46,"row_count":1,"visible":true,"expansion_state":0,"options":{},"document_id":"B93345BE","chunk_id":"cz0km6ns5adt6","chunk_label":"unnamed-chunk-4"},{"row":58,"row_count":1,"visible":true,"expansion_state":0,"options":{},"document_id":"B93345BE","chunk_id":"cjifgloyuy2st","chunk_label":"unnamed-chunk-5"},{"row":64,"row_count":1,"visible":true,"expansion_state":0,"options":{},"document_id":"B93345BE","chunk_id":"c3021ylzmmjib","chunk_label":"unnamed-chunk-6"},{"row":69,"row_count":1,"visible":true,"expansion_state":0,"options":{},"document_id":"B93345BE","chunk_id":"c0dhgh45wl8xp","chunk_label":"unnamed-chunk-7"},{"row":79,"row_count":1,"visible":true,"expansion_state":0,"options":{},"document_id":"B93345BE","chunk_id":"cc7hyv0ab6tgk","chunk_label":"unnamed-chunk-8"},{"row":84,"row_count":1,"visible":true,"expansion_state":0,"options":{},"document_id":"B93345BE","chunk_id":"c1wjij27hf3ay","chunk_label":"unnamed-chunk-9"},{"row":89,"row_count":1,"visible":true,"expansion_state":0,"options":{},"document_id":"B93345BE","chunk_id":"c97693o7afagg","chunk_label":"unnamed-chunk-10"}],"doc_write_time":1676758124}